{
  "title": "React Sample",
  "header": {
    "0": {
      "@name": "0",
      "@path": "/react-sample/header/0",
      "@id": "4c84d839-dfa8-439b-8210-bffa586d556e",
      "@nodeType": "mgnl:component",
      "mgnl:createdBy": "superuser",
      "jcr:createdBy": "admin",
      "mgnl:lastModified": "2020-01-15T10:00:31.890+07:00",
      "mgnl:activationStatus": "true",
      "mgnl:template": "sample-light-module:components/navigation",
      "jcr:created": "2020-01-15T10:00:31.890+07:00",
      "mgnl:lastActivated": "2020-01-17T09:00:46.011+07:00",
      "mgnl:created": "2020-01-15T10:00:31.890+07:00",
      "mgnl:lastModifiedBy": "superuser",
      "@nodes": []
    },
    "@name": "header",
    "@path": "/react-sample/header",
    "@id": "42c4e928-36d0-4383-a57b-354c8e7b362c",
    "@nodeType": "mgnl:area",
    "mgnl:createdBy": "superuser",
    "jcr:createdBy": "admin",
    "mgnl:lastModified": "2020-01-15T10:00:31.890+07:00",
    "mgnl:activationStatus": "true",
    "jcr:created": "2020-01-15T10:00:26.039+07:00",
    "mgnl:lastActivated": "2020-01-17T09:00:46.010+07:00",
    "mgnl:created": "2020-01-15T10:00:26.040+07:00",
    "mgnl:lastModifiedBy": "superuser",
    "@nodes": ["0"]
  },
  "main": {
    "0": {
      "@name": "0",
      "@path": "/react-sample/main/0",
      "@id": "1270f0d7-f52e-4f93-a96b-685b12ac7e89",
      "@nodeType": "mgnl:component",
      "mgnl:createdBy": "superuser",
      "jcr:createdBy": "admin",
      "title": "Test",
      "mgnl:lastModified": "2020-01-21T14:12:23.758+07:00",
      "mgnl:activationStatus": "true",
      "mgnl:lastActivated": "2020-01-17T09:00:46.012+07:00",
      "mgnl:template": "sample-light-module:components/nested",
      "jcr:created": "2020-01-21T14:06:58.118+07:00",
      "mgnl:created": "2020-01-21T14:06:58.119+07:00",
      "mgnl:lastModifiedBy": "superuser",
      "nestedArea": {
        "0": {
          "@name": "0",
          "@path": "/react-sample/main/0/nestedArea/0",
          "@id": "0ff53321-3f1e-4d70-8fa1-6a9de17456d9",
          "@nodeType": "mgnl:component",
          "mgnl:createdBy": "superuser",
          "jcr:createdBy": "admin",
          "title": "Child",
          "mgnl:lastModified": "2020-01-21T14:12:23.759+07:00",
          "mgnl:template": "sample-light-module:components/title",
          "jcr:created": "2020-01-21T14:12:23.758+07:00",
          "mgnl:created": "2020-01-21T14:12:23.759+07:00",
          "mgnl:lastModifiedBy": "superuser",
          "@nodes": []
        },
        "@name": "nestedArea",
        "@path": "/react-sample/main/0/nestedArea",
        "@id": "5b44f124-c2c3-4450-b50f-75d6fad6454f",
        "@nodeType": "mgnl:area",
        "mgnl:createdBy": "superuser",
        "jcr:createdBy": "admin",
        "mgnl:lastModified": "2020-01-21T14:12:23.758+07:00",
        "jcr:created": "2020-01-21T14:06:58.171+07:00",
        "mgnl:lastModifiedBy": "superuser",
        "mgnl:created": "2020-01-21T14:06:58.172+07:00",
        "@nodes": ["0"]
      },
      "@nodes": ["nestedArea"]
    },
    "@name": "main",
    "@path": "/react-sample/main",
    "@id": "98339ef4-4356-407d-a639-4fbf7832dfa8",
    "@nodeType": "mgnl:area",
    "mgnl:createdBy": "superuser",
    "jcr:createdBy": "admin",
    "mgnl:lastModified": "2020-02-19T10:57:25.325+07:00",
    "mgnl:activationStatus": "true",
    "jcr:created": "2020-01-15T10:00:26.040+07:00",
    "mgnl:lastActivated": "2020-01-17T09:00:46.012+07:00",
    "mgnl:created": "2020-01-15T10:00:26.041+07:00",
    "mgnl:lastModifiedBy": "superuser",
    "00": {
      "@name": "00",
      "@path": "/react-sample/main/00",
      "@id": "04b18855-d556-448f-9829-8dd275958dca",
      "@nodeType": "mgnl:component",
      "mgnl:createdBy": "superuser",
      "jcr:createdBy": "admin",
      "title": "Test title 1",
      "mgnl:lastModified": "2020-02-19T10:55:51.201+07:00",
      "mgnl:activationStatus": "true",
      "mgnl:lastActivated": "2020-02-19T11:00:46.012+07:00",
      "mgnl:template": "sample-light-module:components/title",
      "jcr:created": "2020-02-19T10:55:51.200+07:00",
      "mgnl:created": "2020-02-19T10:55:51.201+07:00",
      "mgnl:lastModifiedBy": "superuser",
      "@nodes": []
    },
    "01": {
      "@name": "01",
      "@path": "/react-sample/main/01",
      "@id": "919bbd2c-b62e-43da-a5d4-3d028445fc12",
      "@nodeType": "mgnl:component",
      "mgnl:createdBy": "superuser",
      "jcr:createdBy": "admin",
      "title": "Test title 2",
      "mgnl:lastModified": "2020-02-19T10:56:11.102+07:00",
      "mgnl:template": "sample-light-module:components/title",
      "jcr:created": "2020-02-19T10:56:11.100+07:00",
      "mgnl:created": "2020-02-19T10:56:11.102+07:00",
      "mgnl:lastModifiedBy": "superuser",
      "@nodes": []
    },
    "02": {
      "@name": "02",
      "@path": "/react-sample/main/02",
      "@id": "10ce8254-db88-4e82-8d0c-b28d1e3383f4",
      "@nodeType": "mgnl:component",
      "mgnl:createdBy": "superuser",
      "jcr:createdBy": "admin",
      "title": "Test title 3",
      "mgnl:lastModified": "2020-02-19T10:57:25.326+07:00",
      "mgnl:template": "sample-light-module:components/title",
      "jcr:created": "2020-02-19T10:57:25.325+07:00",
      "mgnl:created": "2020-02-19T10:57:25.326+07:00",
      "mgnl:lastModifiedBy": "superuser",
      "@nodes": []
    },
    "@nodes": ["0", "00", "01", "02"]
  },
  "secondary": {
    "@name": "secondary",
    "@path": "/react-sample/secondary",
    "@id": "1ceb02e8-5b15-4663-97e4-6c7b3f3f16e1",
    "@nodeType": "mgnl:area",
    "mgnl:createdBy": "superuser",
    "jcr:createdBy": "admin",
    "mgnl:lastModified": "2020-01-15T10:00:26.041+07:00",
    "mgnl:activationStatus": "true",
    "jcr:created": "2020-01-15T10:00:26.041+07:00",
    "mgnl:lastActivated": "2020-01-17T09:00:46.014+07:00",
    "mgnl:created": "2020-01-15T10:00:26.041+07:00",
    "mgnl:lastModifiedBy": "superuser",
    "@nodes": []
  },
  "single": {
    "@name": "single",
    "@path": "/react-sample/single",
    "@id": "407c84ac-bffe-4732-9954-16c0df2e2ce3",
    "@nodeType": "mgnl:area",
    "mgnl:createdBy": "superuser",
    "jcr:createdBy": "admin",
    "mgnl:lastModified": "2020-01-15T10:00:26.042+07:00",
    "mgnl:activationStatus": "true",
    "jcr:created": "2020-01-15T10:00:26.042+07:00",
    "mgnl:lastActivated": "2020-01-17T09:00:46.015+07:00",
    "mgnl:created": "2020-01-15T10:00:26.042+07:00",
    "mgnl:lastModifiedBy": "superuser",
    "@nodes": []
  },
  "noComponent": {
    "@name": "noComponent",
    "@path": "/react-sample/noComponent",
    "@id": "0a5698c0-bf68-43da-8154-e411e5a87d51",
    "@nodeType": "mgnl:area",
    "mgnl:createdBy": "superuser",
    "jcr:createdBy": "admin",
    "mgnl:lastModified": "2020-01-15T10:00:26.042+07:00",
    "mgnl:activationStatus": "true",
    "jcr:created": "2020-01-15T10:00:26.042+07:00",
    "mgnl:lastActivated": "2020-01-17T09:00:46.016+07:00",
    "mgnl:created": "2020-01-15T10:00:26.042+07:00",
    "mgnl:lastModifiedBy": "superuser",
    "@nodes": []
  },
  "noComponentNoCreatedNode": {
    "@name": "noComponentNoCreatedNode",
    "@path": "/react-sample/noComponentNoCreatedNode",
    "@id": "44fc8ce5-5b1a-445a-a704-f534bb72f7d8",
    "@nodeType": "mgnl:area",
    "mgnl:createdBy": "superuser",
    "jcr:createdBy": "admin",
    "mgnl:lastModified": "2020-01-15T10:00:26.043+07:00",
    "mgnl:activationStatus": "true",
    "jcr:created": "2020-01-15T10:00:26.043+07:00",
    "mgnl:lastActivated": "2020-01-17T09:00:46.016+07:00",
    "mgnl:lastModifiedBy": "superuser",
    "mgnl:created": "2020-01-15T10:00:26.043+07:00",
    "@nodes": []
  },
  "nestedAreas": {
    "@name": "nestedAreas",
    "@path": "/react-sample/nestedAreas",
    "@id": "0616741f-ad35-4090-99ee-f8aa18f220f0",
    "@nodeType": "mgnl:area",
    "mgnl:createdBy": "superuser",
    "jcr:createdBy": "admin",
    "mgnl:lastModified": "2020-01-15T10:00:26.044+07:00",
    "mgnl:activationStatus": "true",
    "jcr:created": "2020-01-15T10:00:26.043+07:00",
    "mgnl:lastActivated": "2020-01-17T09:00:46.017+07:00",
    "mgnl:lastModifiedBy": "superuser",
    "mgnl:created": "2020-01-15T10:00:26.044+07:00",
    "@nodes": []
  },
  "nestedArea": {
    "@name": "nestedArea",
    "@path": "/react-sample/nestedArea",
    "@id": "0ea93730-61bf-44f1-b8a6-f155d0f2394f",
    "@nodeType": "mgnl:area",
    "mgnl:createdBy": "superuser",
    "jcr:createdBy": "admin",
    "mgnl:lastModified": "2020-01-21T11:26:29.461+07:00",
    "jcr:created": "2020-01-21T11:26:29.460+07:00",
    "mgnl:created": "2020-01-21T11:26:29.461+07:00",
    "mgnl:lastModifiedBy": "superuser",
    "@nodes": []
  },
  "metadata": {
    "@name": "react-sample",
    "@path": "/react-sample",
    "@id": "c2c4f24f-ff28-40df-8c7c-5d71fe040465",
    "@nodeType": "mgnl:page",
    "mgnl:createdBy": "superuser",
    "jcr:createdBy": "admin",
    "mgnl:lastModified": "2020-02-19T10:57:25.325+07:00",
    "mgnl:activationStatus": "true",
    "mgnl:template": "sample-light-module:pages/standard",
    "jcr:created": "2020-01-15T09:59:17.313+07:00",
    "mgnl:lastActivated": "2020-01-17T09:00:46.008+07:00",
    "mgnl:created": "2020-01-15T09:59:17.314+07:00",
    "mgnl:lastModifiedBy": "superuser",
    "@nodes": [
      "header",
      "main",
      "secondary",
      "single",
      "noComponent",
      "noComponentNoCreatedNode",
      "nestedAreas",
      "nestedArea"
    ]
  }
}
